adafruit_dymoscale.py
adafruit_circuitpython_dymoscale-2.0.12.dist-info/licenses/LICENSE
adafruit_circuitpython_dymoscale-2.0.12.dist-info/METADATA
adafruit_circuitpython_dymoscale-2.0.12.dist-info/WHEEL
adafruit_circuitpython_dymoscale-2.0.12.dist-info/top_level.txt
adafruit_circuitpython_dymoscale-2.0.12.dist-info/RECORD
